study_id_generator/__init__.py
study_id_generator/__main__.py
study_id_generator-0.0.5.dist-info/METADATA
study_id_generator-0.0.5.dist-info/WHEEL
study_id_generator-0.0.5.dist-info/top_level.txt
study_id_generator-0.0.5.dist-info/RECORD
