Metadata-Version: 2.1
Name: study-id-generator
Version: 0.0.5
Summary: Study ID Generator.
Author-email: Sushant Obeja <sobeja@umich.edu>, Adam Patterson <adpatter@umich.edu>
Project-URL: Homepage, https://git.umms.med.umich.edu/feldman-lab/study_id_generator
Project-URL: Bug Tracker, https://git.umms.med.umich.edu/feldman-lab/study_id_generator/-/issues
Classifier: Programming Language :: Python :: 3
Classifier: License :: OSI Approved :: MIT License
Classifier: Operating System :: OS Independent
Requires-Python: >=3.8
Requires-Dist: requests (<3,>=2.28)
Requires-Dist: scikit-learn (<2,>=1.1)
Requires-Dist: pandas (<2,>=1.5)
Requires-Dist: numpy (<2,>=1.23)
Requires-Dist: wxpython (<5,>=4.1)
